LICENSE
README.md
setup.py
ntier/__init__.py
ntier/constants.py
ntier/deserialize.py
ntier/deserialize_html.py
ntier/interaction_base.py
ntier/messages.py
ntier/paging.py
ntier/policy_result.py
ntier/py.typed
ntier/serialize.py
ntier/transaction_base.py
ntier/transaction_code.py
ntier/transaction_result.py
ntier/validation_result.py
ntier/validator.py
ntier.egg-info/PKG-INFO
ntier.egg-info/SOURCES.txt
ntier.egg-info/dependency_links.txt
ntier.egg-info/not-zip-safe
ntier.egg-info/requires.txt
ntier.egg-info/top_level.txt